README.md
setup.py
melis_tfidf_transformer.egg-info/PKG-INFO
melis_tfidf_transformer.egg-info/SOURCES.txt
melis_tfidf_transformer.egg-info/dependency_links.txt
melis_tfidf_transformer.egg-info/requires.txt
melis_tfidf_transformer.egg-info/top_level.txt
tfidf/Corpus.py
tfidf/Document.py
tfidf/__init__.py