Metadata-Version: 2.1
Name: melis-tfidf-transformer
Version: 0.0.1
Summary: A package for doing tf-idf transformations.
Author: Melis Kızıldemir
